genppi_py/__init__.py
genppi_py/cli.py
genppi_py/download_model.py
genppi_py/download_model_direct.py
genppi_py/download_samples.py
genppi_py/genppi.py
genppi_py/bin/__init__.py
genppi_py/bin/genppi32g-Linux
genppi_py/bin/genppidb32g-Linux
genppi_py-0.1.7.dist-info/METADATA
genppi_py-0.1.7.dist-info/WHEEL
genppi_py-0.1.7.dist-info/entry_points.txt
genppi_py-0.1.7.dist-info/top_level.txt
genppi_py-0.1.7.dist-info/RECORD
