Metadata-Version: 2.4
Name: genppi-py
Version: 0.1.7
Summary: Python interface for GenPPI (Genomic-based Protein-Protein Interaction prediction)
Author-email: GenPPI Team <example@example.com>
License: GPL-3.0-or-later
Project-URL: Homepage, https://github.com/santosardr/genppi
Project-URL: Repository, https://github.com/santosardr/genppi
Project-URL: Issues, https://github.com/santosardr/genppi/issues
Classifier: Development Status :: 4 - Beta
Classifier: Intended Audience :: Science/Research
Classifier: License :: OSI Approved :: GNU General Public License v3 (GPLv3)
Classifier: Programming Language :: Python :: 3
Classifier: Programming Language :: Python :: 3.8
Classifier: Programming Language :: Python :: 3.9
Classifier: Programming Language :: Python :: 3.10
Classifier: Programming Language :: Python :: 3.11
Classifier: Programming Language :: Python :: 3.12
Classifier: Topic :: Scientific/Engineering :: Bio-Informatics
Requires-Python: >=3.8
Requires-Dist: py7zr<1.0.0,>=0.20.0
Requires-Dist: multivolumefile>=0.2.3
